README.md
setup.py
mongotocsv/__init__.py
mongotocsv/mongotocsv.py
mongotocsv.egg-info/PKG-INFO
mongotocsv.egg-info/SOURCES.txt
mongotocsv.egg-info/dependency_links.txt
mongotocsv.egg-info/requires.txt
mongotocsv.egg-info/top_level.txt