Metadata-Version: 1.1
Name: mongotocsv
Version: 0.1.3
Summary: Creates a CSV file from a MongoDB collection
Home-page: https://github.com/BlackIsBlack/mongotocsv
Author: Cameron Jensen
Author-email: cameron@situ.com.au
License: BSD 2-clause
Platform: UNKNOWN
Classifier: Programming Language :: Python :: 3.10
